routir/__init__.py
routir/check_offset_maps.py
routir/prewarm_cache.py
routir/serve.py
routir/config/__init__.py
routir/config/config.py
routir/config/load.py
routir/models/__init__.py
routir/models/abstract.py
routir/models/fusion.py
routir/models/lsr.py
routir/models/mt5.py
routir/models/plaidx.py
routir/models/qwen3.py
routir/models/qwen3reranker.py
routir/models/relay.py
routir/models/llm_rerankers/__init__.py
routir/models/llm_rerankers/generic.py
routir/models/llm_rerankers/prompts.py
routir/pipeline/__init__.py
routir/pipeline/parser.py
routir/pipeline/pipeline.py
routir/processors/__init__.py
routir/processors/abstract.py
routir/processors/cache.py
routir/processors/content_processors.py
routir/processors/query_processors.py
routir/processors/registry.py
routir/processors/score_processors.py
routir/utils/__init__.py
routir/utils/evaluate_pipeline.py
routir/utils/extensions.py
routir/utils/faiss_indexing.py
routir/utils/file_io.py
routir/utils/lazy_import.py
routir/utils/qwen3_encode.py
routir-0.0.1.dist-info/licenses/LICENSE
routir-0.0.1.dist-info/METADATA
routir-0.0.1.dist-info/WHEEL
routir-0.0.1.dist-info/entry_points.txt
routir-0.0.1.dist-info/top_level.txt
routir-0.0.1.dist-info/RECORD
