Metadata-Version: 2.4
Name: routir
Version: 0.0.1
Summary: A simple and fast search service for hosting state-of-the-art retrieval models.
Author-email: Eugene Yang <eugene.yang@jhu.edu>
Maintainer-email: Eugene Yang <eugene.yang@jhu.edu>
License: MIT
Keywords: search,retrieval,service
Requires-Python: >=3.9
License-File: LICENSE
Requires-Dist: lark
Requires-Dist: quart
Requires-Dist: trecrun
Requires-Dist: hypercorn
Requires-Dist: openai
Requires-Dist: aiohttp
Requires-Dist: tqdm
Requires-Dist: pydantic
Requires-Dist: huggingface_hub
Requires-Dist: hf_xet
Provides-Extra: dense
Requires-Dist: numpy; extra == "dense"
Requires-Dist: faiss-cpu; extra == "dense"
Provides-Extra: gpu
Requires-Dist: faiss-gpu; extra == "gpu"
Requires-Dist: torch; extra == "gpu"
Provides-Extra: plaidx
Requires-Dist: plaid-x; extra == "plaidx"
Provides-Extra: sparse
Requires-Dist: pyjnius==1.6.1; extra == "sparse"
Requires-Dist: bsparse; extra == "sparse"
Provides-Extra: docs
Requires-Dist: sphinx>=4.0; extra == "docs"
Requires-Dist: sphinx-rtd-theme>=0.5; extra == "docs"
Requires-Dist: myst-parser>=0.18; extra == "docs"
Dynamic: license-file
